oc_mailer/Mailer.py
oc_mailer/__init__.py
oc_mailer/resources/config.json
oc_mailer-1.0.1.dist-info/LICENSE
oc_mailer-1.0.1.dist-info/METADATA
oc_mailer-1.0.1.dist-info/WHEEL
oc_mailer-1.0.1.dist-info/top_level.txt
oc_mailer-1.0.1.dist-info/RECORD
