Metadata-Version: 2.1
Name: oc-mailer
Version: 1.0.1
Summary: SMTP mailer class for senging auto-notifications with pre-defined templates
License: LGPLv2
Requires-Python: >=3.6
License-File: LICENSE
